seq_detector1011.v
// Code your design here
module seq_detector1011(
  input wire clk,
  input wire reset,
  input wire inp,
  output reg out
);
  
  reg [2:0] present_state, next_state;
  parameter S0 = 3'b000, S1 = 3'b001, S2 = 3'b010, S3 = 3'b011, S4 = 3'b100;
  
  //logic for present state
  always @(posedge clk)
    begin 
      if (reset)
        begin
          present_state <= S0;
        end
      else
        begin
          present_state <= next_state;
        end
    end
  //logic for next state
  always @(*)
    begin
      case(present_state)
        S0: begin
          if(inp)
            next_state = S1;
          else
            next_state = S0;
        end
        S1: begin
          if(inp)
            next_state = S1;
          else
            next_state = S2;
        end
        S2: begin
          if(inp)
            next_state = S3;
          else
            next_state = S0;
        end
        S3: begin
          if(inp)
            next_state = S4;
          else
            next_state = S3;
        end
        S4: begin
          if(inp)
            next_state = S4;
          else
            next_state = S2;
        end
      endcase
    end
  
  // logic for output
  always @(*)
    begin
      case(present_state)
        S0:  out = 0; 
        S1:  out = 0; 
        S2:  out = 0; 
        S3:  out = 0; 
        S4:  out = 1; 
        default: out = 0;
    endcase
    end
endmodule

tb_seq_detector1011.v
module seq_detector1011_tb;
    // Inputs and outputs
    reg clk;
    reg reset;
    reg inp;
    wire out;

    // Instantiation
    seq_detector1011 DUT (
      .clk(clk),
      .reset(reset),
      .inp(inp),
      .out(out)
    );
  
  // Clock generation
  always begin 
    #5 clk = ~clk;
  end
  
  // Initialization
  initial begin
    clk = 0;
    reset = 1; 
    inp  = 0;
    #10 reset = 0; 
    
    // Test sequence "1011"
    #10 inp = 1; 
    #10 inp = 0; 
    #10 inp = 1; 
    #10 inp = 1; 
    #10 inp = 0; 
    #10 inp = 1; 
    #10 inp = 1; 
  end

  initial begin 
    $dumpfile("dump.vcd");
    $dumpvars(0);
    #120;
    $finish;
  end
endmodule

dump.vcd
$date
	Sat Mar 23 19:54:51 2024
$end
$version
	Icarus Verilog
$end
$timescale
	1s
$end
$scope module seq_detector1011_tb $end
$var wire 1 ! out $end
$var reg 1 " clk $end
$var reg 1 # inp $end
$var reg 1 $ reset $end
$scope module DUT $end
$var wire 1 " clk $end
$var wire 1 # inp $end
$var wire 1 $ reset $end
$var reg 3 % next_state [2:0] $end
$var reg 1 ! out $end
$var reg 3 & present_state [2:0] $end
$upscope $end
$upscope $end
$enddefinitions $end
#0
$dumpvars
bx &
bx %
1$
0#
0"
x!
$end
#5
0!
b0 %
b0 &
1"
#10
0"
0$
#15
1"
#20
b1 %
0"
1#
#25
b1 &
1"
#30
b10 %
0"
0#
#35
b0 %
b10 &
1"
#40
b11 %
0"
1#
#45
b100 %
b11 &
1"
#50
0"
#55
1!
b1 %
b100 &
1"
#60
b10 %
0"
0#
#65
0!
b0 %
b10 &
1"
#70
b11 %
0"
1#
#75
b100 %
b11 &
1"
#80
0"
#85
1!
b1 %
b100 &
1"
#90
0"
#95
0!
b1 &
1"
